[
  {
    "title": "a-ha_-_Take_On_Me_(Official_Video)_[4K",
    "url": "https://www.youtube.com/watch?v=djV11Xbc914",
    "format_id": "401",
    "format_type": "Video",
    "output_path": "C:\Users\Guesty\Documents\VDM_IMGUI_TESTING\a-ha_-_Take_On_Me_(Official_Video)_[4K.mkv",
    "status": "Completed",
    "file_size": "",
    "added_time": "2025-09-17 18:22:40",
    "start_time": "",
    "end_time": "2025-09-17 18:23:18"
  },
  {
    "title": "The_Chemical_Brothers_-_The_Test_(Official_Music_Video",
    "url": "https://www.youtube.com/watch?v=yhS9LnDoo_w",
    "format_id": "140",
    "format_type": "Audio",
    "output_path": "C:\Users\Guesty\Downloads\The_Chemical_Brothers_-_The_Test_(Official_Music_Video.m4a",
    "status": "Completed",
    "file_size": "",
    "added_time": "2025-09-17 17:53:41",
    "start_time": "",
    "end_time": "2025-09-17 17:53:50"
  }
]
